rtl/pe.v
module pe (
    input  wire        clk, rst_n,
    input  wire        en,
    input  wire [7:0]  a_in,      // from left
    input  wire [7:0]  w_in,      // weight from top
    output reg  [7:0]  a_out,     // pass right
    output reg  [7:0]  w_out,     // pass down
    output reg  [31:0] acc        // accumulated sum
);
    always @(posedge clk or negedge rst_n) begin
        if (!rst_n) begin
            a_out <= 0;
            w_out <= 0;
            acc   <= 0;
        end else if (en) begin
            a_out <= a_in;           // pass activation right
            w_out <= w_in;           // pass weight down
            acc   <= acc + (a_in * w_in);  // MAC
        end
    end
endmodule

rtl/systolic_4x4.v
module systolic_4x4 (
    input  wire        clk, rst_n, en,
    // Row inputs (activations) - one per row
    input  wire [7:0]  a_row0, a_row1, a_row2, a_row3,
    // Col inputs (weights) - one per col
    input  wire [7:0]  w_col0, w_col1, w_col2, w_col3,
    // Output accumulators - all 16 results
    output wire [31:0] out_00, out_01, out_02, out_03,
    output wire [31:0] out_10, out_11, out_12, out_13,
    output wire [31:0] out_20, out_21, out_22, out_23,
    output wire [31:0] out_30, out_31, out_32, out_33
);
    // Horizontal wires (activations flowing right)
    wire [7:0] a_00_01, a_01_02, a_02_03;
    wire [7:0] a_10_11, a_11_12, a_12_13;
    wire [7:0] a_20_21, a_21_22, a_22_23;
    wire [7:0] a_30_31, a_31_32, a_32_33;

    // Vertical wires (weights flowing down)
    wire [7:0] w_00_10, w_10_20, w_20_30;
    wire [7:0] w_01_11, w_11_21, w_21_31;
    wire [7:0] w_02_12, w_12_22, w_22_32;
    wire [7:0] w_03_13, w_13_23, w_23_33;

    // Row 0
    pe pe_00(.clk(clk),.rst_n(rst_n),.en(en),.a_in(a_row0),.w_in(w_col0),.a_out(a_00_01),.w_out(w_00_10),.acc(out_00));
    pe pe_01(.clk(clk),.rst_n(rst_n),.en(en),.a_in(a_00_01),.w_in(w_col1),.a_out(a_01_02),.w_out(w_01_11),.acc(out_01));
    pe pe_02(.clk(clk),.rst_n(rst_n),.en(en),.a_in(a_01_02),.w_in(w_col2),.a_out(a_02_03),.w_out(w_02_12),.acc(out_02));
    pe pe_03(.clk(clk),.rst_n(rst_n),.en(en),.a_in(a_02_03),.w_in(w_col3),.a_out(),.w_out(w_03_13),.acc(out_03));

    // Row 1
    pe pe_10(.clk(clk),.rst_n(rst_n),.en(en),.a_in(a_row1),.w_in(w_00_10),.a_out(a_10_11),.w_out(w_10_20),.acc(out_10));
    pe pe_11(.clk(clk),.rst_n(rst_n),.en(en),.a_in(a_10_11),.w_in(w_01_11),.a_out(a_11_12),.w_out(w_11_21),.acc(out_11));
    pe pe_12(.clk(clk),.rst_n(rst_n),.en(en),.a_in(a_11_12),.w_in(w_02_12),.a_out(a_12_13),.w_out(w_12_22),.acc(out_12));
    pe pe_13(.clk(clk),.rst_n(rst_n),.en(en),.a_in(a_12_13),.w_in(w_03_13),.a_out(),.w_out(w_13_23),.acc(out_13));

    // Row 2
    pe pe_20(.clk(clk),.rst_n(rst_n),.en(en),.a_in(a_row2),.w_in(w_10_20),.a_out(a_20_21),.w_out(w_20_30),.acc(out_20));
    pe pe_21(.clk(clk),.rst_n(rst_n),.en(en),.a_in(a_20_21),.w_in(w_11_21),.a_out(a_21_22),.w_out(w_21_31),.acc(out_21));
    pe pe_22(.clk(clk),.rst_n(rst_n),.en(en),.a_in(a_21_22),.w_in(w_12_22),.a_out(a_22_23),.w_out(w_22_32),.acc(out_22));
    pe pe_23(.clk(clk),.rst_n(rst_n),.en(en),.a_in(a_22_23),.w_in(w_13_23),.a_out(),.w_out(w_23_33),.acc(out_23));

    // Row 3
    pe pe_30(.clk(clk),.rst_n(rst_n),.en(en),.a_in(a_row3),.w_in(w_20_30),.a_out(a_30_31),.w_out(),.acc(out_30));
    pe pe_31(.clk(clk),.rst_n(rst_n),.en(en),.a_in(a_30_31),.w_in(w_21_31),.a_out(a_31_32),.w_out(),.acc(out_31));
    pe pe_32(.clk(clk),.rst_n(rst_n),.en(en),.a_in(a_31_32),.w_in(w_22_32),.a_out(a_32_33),.w_out(),.acc(out_32));
    pe pe_33(.clk(clk),.rst_n(rst_n),.en(en),.a_in(a_32_33),.w_in(w_23_33),.a_out(),.w_out(),.acc(out_33));

endmodule

tb/tb_systolic2.v
`timescale 1ns/1ns
module tb_systolic2;

    reg clk, rst_n, en;
    reg [7:0] a_row0, a_row1, a_row2, a_row3;
    reg [7:0] w_col0, w_col1, w_col2, w_col3;

    wire [31:0] out_00, out_01, out_02, out_03;
    wire [31:0] out_10, out_11, out_12, out_13;
    wire [31:0] out_20, out_21, out_22, out_23;
    wire [31:0] out_30, out_31, out_32, out_33;

    systolic_4x4 dut (
        .clk(clk), .rst_n(rst_n), .en(en),
        .a_row0(a_row0), .a_row1(a_row1),
        .a_row2(a_row2), .a_row3(a_row3),
        .w_col0(w_col0), .w_col1(w_col1),
        .w_col2(w_col2), .w_col3(w_col3),
        .out_00(out_00), .out_01(out_01),
        .out_02(out_02), .out_03(out_03),
        .out_10(out_10), .out_11(out_11),
        .out_12(out_12), .out_13(out_13),
        .out_20(out_20), .out_21(out_21),
        .out_22(out_22), .out_23(out_23),
        .out_30(out_30), .out_31(out_31),
        .out_32(out_32), .out_33(out_33)
    );

    always #5 clk = ~clk;

    // A matrix
    reg [7:0] A [0:3][0:3];
    // B matrix
    reg [7:0] B [0:3][0:3];
    // Expected C
    integer C [0:3][0:3];
    integer i, j, k, pass, fail;

    initial begin
        $dumpfile("sim/systolic2.vcd");
        $dumpvars(0, tb_systolic2);

        clk=0; rst_n=0; en=0;
        a_row0=0; a_row1=0; a_row2=0; a_row3=0;
        w_col0=0; w_col1=0; w_col2=0; w_col3=0;

        // Matrix A
        A[0][0]=1;  A[0][1]=2;  A[0][2]=3;  A[0][3]=4;
        A[1][0]=5;  A[1][1]=6;  A[1][2]=7;  A[1][3]=8;
        A[2][0]=9;  A[2][1]=10; A[2][2]=11; A[2][3]=12;
        A[3][0]=13; A[3][1]=14; A[3][2]=15; A[3][3]=16;

        // Matrix B (non-trivial)
        B[0][0]=2; B[0][1]=0; B[0][2]=1; B[0][3]=0;
        B[1][0]=0; B[1][1]=3; B[1][2]=0; B[1][3]=1;
        B[2][0]=1; B[2][1]=0; B[2][2]=2; B[2][3]=0;
        B[3][0]=0; B[3][1]=1; B[3][2]=0; B[3][3]=3;

        // Golden C
        C[0][0]=5;  C[0][1]=10; C[0][2]=7;  C[0][3]=14;
        C[1][0]=17; C[1][1]=26; C[1][2]=19; C[1][3]=30;
        C[2][0]=29; C[2][1]=42; C[2][2]=31; C[2][3]=46;
        C[3][0]=41; C[3][1]=58; C[3][2]=43; C[3][3]=62;

        repeat(4) @(posedge clk);
        rst_n = 1; en = 1;
        repeat(2) @(posedge clk);

        // Diagonal skew feeding
        @(posedge clk);
        a_row0=A[0][0]; a_row1=0;       a_row2=0;       a_row3=0;
        w_col0=B[0][0]; w_col1=0;       w_col2=0;       w_col3=0;

        @(posedge clk);
        a_row0=A[0][1]; a_row1=A[1][0]; a_row2=0;       a_row3=0;
        w_col0=B[1][0]; w_col1=B[0][1]; w_col2=0;       w_col3=0;

        @(posedge clk);
        a_row0=A[0][2]; a_row1=A[1][1]; a_row2=A[2][0]; a_row3=0;
        w_col0=B[2][0]; w_col1=B[1][1]; w_col2=B[0][2]; w_col3=0;

        @(posedge clk);
        a_row0=A[0][3]; a_row1=A[1][2]; a_row2=A[2][1]; a_row3=A[3][0];
        w_col0=B[3][0]; w_col1=B[2][1]; w_col2=B[1][2]; w_col3=B[0][3];

        @(posedge clk);
        a_row0=0;       a_row1=A[1][3]; a_row2=A[2][2]; a_row3=A[3][1];
        w_col0=0;       w_col1=B[3][1]; w_col2=B[2][2]; w_col3=B[1][3];

        @(posedge clk);
        a_row0=0;       a_row1=0;       a_row2=A[2][3]; a_row3=A[3][2];
        w_col0=0;       w_col1=0;       w_col2=B[3][2]; w_col3=B[2][3];

        @(posedge clk);
        a_row0=0;       a_row1=0;       a_row2=0;       a_row3=A[3][3];
        w_col0=0;       w_col1=0;       w_col2=0;       w_col3=B[3][3];

        @(posedge clk);
        a_row0=0; a_row1=0; a_row2=0; a_row3=0;
        w_col0=0; w_col1=0; w_col2=0; w_col3=0;
        repeat(5) @(posedge clk);

        // Verify
        pass=0; fail=0;
        $display("\n=== Test 2: Non-Trivial Matrix ===");
        $display("RTL Output:");
        $display("  [%0d, %0d, %0d, %0d]", out_00,out_01,out_02,out_03);
        $display("  [%0d, %0d, %0d, %0d]", out_10,out_11,out_12,out_13);
        $display("  [%0d, %0d, %0d, %0d]", out_20,out_21,out_22,out_23);
        $display("  [%0d, %0d, %0d, %0d]", out_30,out_31,out_32,out_33);
        $display("Expected:");
        $display("  [5, 10, 7, 14]");
        $display("  [17, 26, 19, 30]");
        $display("  [29, 42, 31, 46]");
        $display("  [41, 58, 43, 62]");

        if(out_00==5  && out_01==10 && out_02==7  && out_03==14) begin $display("Row 0: PASS"); pass=pass+1; end
        else begin $display("Row 0: FAIL got [%0d,%0d,%0d,%0d]",out_00,out_01,out_02,out_03); fail=fail+1; end

        if(out_10==17 && out_11==26 && out_12==19 && out_13==30) begin $display("Row 1: PASS"); pass=pass+1; end
        else begin $display("Row 1: FAIL got [%0d,%0d,%0d,%0d]",out_10,out_11,out_12,out_13); fail=fail+1; end

        if(out_20==29 && out_21==42 && out_22==31 && out_23==46) begin $display("Row 2: PASS"); pass=pass+1; end
        else begin $display("Row 2: FAIL got [%0d,%0d,%0d,%0d]",out_20,out_21,out_22,out_23); fail=fail+1; end

        if(out_30==41 && out_31==58 && out_32==43 && out_33==62) begin $display("Row 3: PASS"); pass=pass+1; end
        else begin $display("Row 3: FAIL got [%0d,%0d,%0d,%0d]",out_30,out_31,out_32,out_33); fail=fail+1; end

        $display("\n=== %0d/4 PASS | %0d/4 FAIL ===", pass, fail);
        if (fail==0) $display("*** ALL PASS — Non-Trivial Matrix Verified! ***");

        $finish;
    end
endmodule

sim/systolic2.vcd
$date
	Sun Apr 19 21:24:38 2026
$end
$version
	Icarus Verilog
$end
$timescale
	1ns
$end
$scope module tb_systolic2 $end
$var wire 32 ! out_33 [31:0] $end
$var wire 32 " out_32 [31:0] $end
$var wire 32 # out_31 [31:0] $end
$var wire 32 $ out_30 [31:0] $end
$var wire 32 % out_23 [31:0] $end
$var wire 32 & out_22 [31:0] $end
$var wire 32 ' out_21 [31:0] $end
$var wire 32 ( out_20 [31:0] $end
$var wire 32 ) out_13 [31:0] $end
$var wire 32 * out_12 [31:0] $end
$var wire 32 + out_11 [31:0] $end
$var wire 32 , out_10 [31:0] $end
$var wire 32 - out_03 [31:0] $end
$var wire 32 . out_02 [31:0] $end
$var wire 32 / out_01 [31:0] $end
$var wire 32 0 out_00 [31:0] $end
$var reg 8 1 a_row0 [7:0] $end
$var reg 8 2 a_row1 [7:0] $end
$var reg 8 3 a_row2 [7:0] $end
$var reg 8 4 a_row3 [7:0] $end
$var reg 1 5 clk $end
$var reg 1 6 en $end
$var reg 1 7 rst_n $end
$var reg 8 8 w_col0 [7:0] $end
$var reg 8 9 w_col1 [7:0] $end
$var reg 8 : w_col2 [7:0] $end
$var reg 8 ; w_col3 [7:0] $end
$var integer 32 < fail [31:0] $end
$var integer 32 = pass [31:0] $end
$scope module dut $end
$var wire 8 > a_row0 [7:0] $end
$var wire 8 ? a_row1 [7:0] $end
$var wire 8 @ a_row2 [7:0] $end
$var wire 8 A a_row3 [7:0] $end
$var wire 1 5 clk $end
$var wire 1 6 en $end
$var wire 1 7 rst_n $end
$var wire 8 B w_col0 [7:0] $end
$var wire 8 C w_col1 [7:0] $end
$var wire 8 D w_col2 [7:0] $end
$var wire 8 E w_col3 [7:0] $end
$var wire 8 F w_23_33 [7:0] $end
$var wire 8 G w_22_32 [7:0] $end
$var wire 8 H w_21_31 [7:0] $end
$var wire 8 I w_20_30 [7:0] $end
$var wire 8 J w_13_23 [7:0] $end
$var wire 8 K w_12_22 [7:0] $end
$var wire 8 L w_11_21 [7:0] $end
$var wire 8 M w_10_20 [7:0] $end
$var wire 8 N w_03_13 [7:0] $end
$var wire 8 O w_02_12 [7:0] $end
$var wire 8 P w_01_11 [7:0] $end
$var wire 8 Q w_00_10 [7:0] $end
$var wire 32 R out_33 [31:0] $end
$var wire 32 S out_32 [31:0] $end
$var wire 32 T out_31 [31:0] $end
$var wire 32 U out_30 [31:0] $end
$var wire 32 V out_23 [31:0] $end
$var wire 32 W out_22 [31:0] $end
$var wire 32 X out_21 [31:0] $end
$var wire 32 Y out_20 [31:0] $end
$var wire 32 Z out_13 [31:0] $end
$var wire 32 [ out_12 [31:0] $end
$var wire 32 \ out_11 [31:0] $end
$var wire 32 ] out_10 [31:0] $end
$var wire 32 ^ out_03 [31:0] $end
$var wire 32 _ out_02 [31:0] $end
$var wire 32 ` out_01 [31:0] $end
$var wire 32 a out_00 [31:0] $end
$var wire 8 b a_32_33 [7:0] $end
$var wire 8 c a_31_32 [7:0] $end
$var wire 8 d a_30_31 [7:0] $end
$var wire 8 e a_22_23 [7:0] $end
$var wire 8 f a_21_22 [7:0] $end
$var wire 8 g a_20_21 [7:0] $end
$var wire 8 h a_12_13 [7:0] $end
$var wire 8 i a_11_12 [7:0] $end
$var wire 8 j a_10_11 [7:0] $end
$var wire 8 k a_02_03 [7:0] $end
$var wire 8 l a_01_02 [7:0] $end
$var wire 8 m a_00_01 [7:0] $end
$scope module pe_00 $end
$var wire 8 n a_in [7:0] $end
$var wire 1 5 clk $end
$var wire 1 6 en $end
$var wire 1 7 rst_n $end
$var wire 8 o w_in [7:0] $end
$var reg 8 p a_out [7:0] $end
$var reg 32 q acc [31:0] $end
$var reg 8 r w_out [7:0] $end
$upscope $end
$scope module pe_01 $end
$var wire 8 s a_in [7:0] $end
$var wire 1 5 clk $end
$var wire 1 6 en $end
$var wire 1 7 rst_n $end
$var wire 8 t w_in [7:0] $end
$var reg 8 u a_out [7:0] $end
$var reg 32 v acc [31:0] $end
$var reg 8 w w_out [7:0] $end
$upscope $end
$scope module pe_02 $end
$var wire 8 x a_in [7:0] $end
$var wire 1 5 clk $end
$var wire 1 6 en $end
$var wire 1 7 rst_n $end
$var wire 8 y w_in [7:0] $end
$var reg 8 z a_out [7:0] $end
$var reg 32 { acc [31:0] $end
$var reg 8 | w_out [7:0] $end
$upscope $end
$scope module pe_03 $end
$var wire 8 } a_in [7:0] $end
$var wire 1 5 clk $end
$var wire 1 6 en $end
$var wire 1 7 rst_n $end
$var wire 8 ~ w_in [7:0] $end
$var reg 8 !" a_out [7:0] $end
$var reg 32 "" acc [31:0] $end
$var reg 8 #" w_out [7:0] $end
$upscope $end
$scope module pe_10 $end
$var wire 8 $" a_in [7:0] $end
$var wire 1 5 clk $end
$var wire 1 6 en $end
$var wire 1 7 rst_n $end
$var wire 8 %" w_in [7:0] $end
$var reg 8 &" a_out [7:0] $end
$var reg 32 '" acc [31:0] $end
$var reg 8 (" w_out [7:0] $end
$upscope $end
$scope module pe_11 $end
$var wire 8 )" a_in [7:0] $end
$var wire 1 5 clk $end
$var wire 1 6 en $end
$var wire 1 7 rst_n $end
$var wire 8 *" w_in [7:0] $end
$var reg 8 +" a_out [7:0] $end
$var reg 32 ," acc [31:0] $end
$var reg 8 -" w_out [7:0] $end
$upscope $end
$scope module pe_12 $end
$var wire 8 ." a_in [7:0] $end
$var wire 1 5 clk $end
$var wire 1 6 en $end
$var wire 1 7 rst_n $end
$var wire 8 /" w_in [7:0] $end
$var reg 8 0" a_out [7:0] $end
$var reg 32 1" acc [31:0] $end
$var reg 8 2" w_out [7:0] $end
$upscope $end
$scope module pe_13 $end
$var wire 8 3" a_in [7:0] $end
$var wire 1 5 clk $end
$var wire 1 6 en $end
$var wire 1 7 rst_n $end
$var wire 8 4" w_in [7:0] $end
$var reg 8 5" a_out [7:0] $end
$var reg 32 6" acc [31:0] $end
$var reg 8 7" w_out [7:0] $end
$upscope $end
$scope module pe_20 $end
$var wire 8 8" a_in [7:0] $end
$var wire 1 5 clk $end
$var wire 1 6 en $end
$var wire 1 7 rst_n $end
$var wire 8 9" w_in [7:0] $end
$var reg 8 :" a_out [7:0] $end
$var reg 32 ;" acc [31:0] $end
$var reg 8 <" w_out [7:0] $end
$upscope $end
$scope module pe_21 $end
$var wire 8 =" a_in [7:0] $end
$var wire 1 5 clk $end
$var wire 1 6 en $end
$var wire 1 7 rst_n $end
$var wire 8 >" w_in [7:0] $end
$var reg 8 ?" a_out [7:0] $end
$var reg 32 @" acc [31:0] $end
$var reg 8 A" w_out [7:0] $end
$upscope $end
$scope module pe_22 $end
$var wire 8 B" a_in [7:0] $end
$var wire 1 5 clk $end
$var wire 1 6 en $end
$var wire 1 7 rst_n $end
$var wire 8 C" w_in [7:0] $end
$var reg 8 D" a_out [7:0] $end
$var reg 32 E" acc [31:0] $end
$var reg 8 F" w_out [7:0] $end
$upscope $end
$scope module pe_23 $end
$var wire 8 G" a_in [7:0] $end
$var wire 1 5 clk $end
$var wire 1 6 en $end
$var wire 1 7 rst_n $end
$var wire 8 H" w_in [7:0] $end
$var reg 8 I" a_out [7:0] $end
$var reg 32 J" acc [31:0] $end
$var reg 8 K" w_out [7:0] $end
$upscope $end
$scope module pe_30 $end
$var wire 8 L" a_in [7:0] $end
$var wire 1 5 clk $end
$var wire 1 6 en $end
$var wire 1 7 rst_n $end
$var wire 8 M" w_in [7:0] $end
$var reg 8 N" a_out [7:0] $end
$var reg 32 O" acc [31:0] $end
$var reg 8 P" w_out [7:0] $end
$upscope $end
$scope module pe_31 $end
$var wire 8 Q" a_in [7:0] $end
$var wire 1 5 clk $end
$var wire 1 6 en $end
$var wire 1 7 rst_n $end
$var wire 8 R" w_in [7:0] $end
$var reg 8 S" a_out [7:0] $end
$var reg 32 T" acc [31:0] $end
$var reg 8 U" w_out [7:0] $end
$upscope $end
$scope module pe_32 $end
$var wire 8 V" a_in [7:0] $end
$var wire 1 5 clk $end
$var wire 1 6 en $end
$var wire 1 7 rst_n $end
$var wire 8 W" w_in [7:0] $end
$var reg 8 X" a_out [7:0] $end
$var reg 32 Y" acc [31:0] $end
$var reg 8 Z" w_out [7:0] $end
$upscope $end
$scope module pe_33 $end
$var wire 8 [" a_in [7:0] $end
$var wire 1 5 clk $end
$var wire 1 6 en $end
$var wire 1 7 rst_n $end
$var wire 8 \" w_in [7:0] $end
$var reg 8 ]" a_out [7:0] $end
$var reg 32 ^" acc [31:0] $end
$var reg 8 _" w_out [7:0] $end
$upscope $end
$upscope $end
$upscope $end
$enddefinitions $end
#0
$dumpvars
b0 _"
b0 ^"
b0 ]"
b0 \"
b0 ["
b0 Z"
b0 Y"
b0 X"
b0 W"
b0 V"
b0 U"
b0 T"
b0 S"
b0 R"
b0 Q"
b0 P"
b0 O"
b0 N"
b0 M"
b0 L"
b0 K"
b0 J"
b0 I"
b0 H"
b0 G"
b0 F"
b0 E"
b0 D"
b0 C"
b0 B"
b0 A"
b0 @"
b0 ?"
b0 >"
b0 ="
b0 <"
b0 ;"
b0 :"
b0 9"
b0 8"
b0 7"
b0 6"
b0 5"
b0 4"
b0 3"
b0 2"
b0 1"
b0 0"
b0 /"
b0 ."
b0 -"
b0 ,"
b0 +"
b0 *"
b0 )"
b0 ("
b0 '"
b0 &"
b0 %"
b0 $"
b0 #"
b0 ""
b0 !"
b0 ~
b0 }
b0 |
b0 {
b0 z
b0 y
b0 x
b0 w
b0 v
b0 u
b0 t
b0 s
b0 r
b0 q
b0 p
b0 o
b0 n
b0 m
b0 l
b0 k
b0 j
b0 i
b0 h
b0 g
b0 f
b0 e
b0 d
b0 c
b0 b
b0 a
b0 `
b0 _
b0 ^
b0 ]
b0 \
b0 [
b0 Z
b0 Y
b0 X
b0 W
b0 V
b0 U
b0 T
b0 S
b0 R
b0 Q
b0 P
b0 O
b0 N
b0 M
b0 L
b0 K
b0 J
b0 I
b0 H
b0 G
b0 F
b0 E
b0 D
b0 C
b0 B
b0 A
b0 @
b0 ?
b0 >
bx =
bx <
b0 ;
b0 :
b0 9
b0 8
07
06
05
b0 4
b0 3
b0 2
b0 1
b0 0
b0 /
b0 .
b0 -
b0 ,
b0 +
b0 *
b0 )
b0 (
b0 '
b0 &
b0 %
b0 $
b0 #
b0 "
b0 !
$end
#5
15
#10
05
#15
15
#20
05
#25
15
#30
05
#35
16
17
15
#40
05
#45
15
#50
05
#55
15
#60
05
#65
b10 0
b10 a
b10 q
b10 Q
b10 r
b10 %"
b1 m
b1 p
b1 s
b10 8
b10 B
b10 o
b1 1
b1 >
b1 n
15
#70
05
#75
b0 Q
b0 r
b0 %"
b10 m
b10 p
b10 s
b1 l
b1 u
b1 x
b1010 ,
b1010 ]
b1010 '"
b10 M
b10 ("
b10 9"
b101 j
b101 &"
b101 )"
b0 8
b0 B
b0 o
b101 2
b101 ?
b101 $"
b10 1
b10 >
b10 n
15
#80
05
#85
b10010 (
b10010 Y
b10010 ;"
b10 I
b10 <"
b10 M"
b1001 g
b1001 :"
b1001 ="
b101 i
b101 +"
b101 ."
b0 M
b0 ("
b0 9"
b110 j
b110 &"
b110 )"
b1 .
b1 _
b1 {
b1 O
b1 |
b1 /"
b1 k
b1 z
b1 }
b110 /
b110 `
b110 v
b11 P
b11 w
b11 *"
b10 l
b10 u
b10 x
b101 0
b101 a
b101 q
b1 Q
b1 r
b1 %"
b11 m
b11 p
b11 s
b1 :
b1 D
b1 y
b11 9
b11 C
b11 t
b1 8
b1 B
b1 o
b1001 3
b1001 @
b1001 8"
b110 2
b110 ?
b110 $"
b11 1
b11 >
b11 n
15
#90
05
#95
b0 Q
b0 r
b0 %"
b100 m
b100 p
b100 s
b0 P
b0 w
b0 *"
b11 l
b11 u
b11 x
b0 O
b0 |
b0 /"
b10 k
b10 z
b10 }
b1 !"
b10001 ,
b10001 ]
b10001 '"
b1 M
b1 ("
b1 9"
b111 j
b111 &"
b111 )"
b10010 +
b10010 \
b10010 ,"
b11 L
b11 -"
b11 >"
b110 i
b110 +"
b110 ."
b101 *
b101 [
b101 1"
b1 K
b1 2"
b1 C"
b101 h
b101 0"
b101 3"
b0 I
b0 <"
b0 M"
b1010 g
b1010 :"
b1010 ="
b1001 f
b1001 ?"
b1001 B"
b11010 $
b11010 U
b11010 O"
b10 P"
b1101 d
b1101 N"
b1101 Q"
b0 :
b0 D
b0 y
b0 9
b0 C
b0 t
b0 8
b0 B
b0 o
b1101 4
b1101 A
b1101 L"
b1010 3
b1010 @
b1010 8"
b111 2
b111 ?
b111 $"
b100 1
b100 >
b100 n
15
#100
05
#105
b1101 c
b1101 S"
b1101 V"
b0 P"
b1110 d
b1110 N"
b1110 Q"
b1001 &
b1001 W
b1001 E"
b1 G
b1 F"
b1 W"
b1001 e
b1001 D"
b1001 G"
b11110 '
b11110 X
b11110 @"
b11 H
b11 A"
b11 R"
b1010 f
b1010 ?"
b1010 B"
b11101 (
b11101 Y
b11101 ;"
b1 I
b1 <"
b1 M"
b1011 g
b1011 :"
b1011 ="
b101 5"
b0 K
b0 2"
b0 C"
b110 h
b110 0"
b110 3"
b0 L
b0 -"
b0 >"
b111 i
b111 +"
b111 ."
b0 M
b0 ("
b0 9"
b1000 j
b1000 &"
b1000 )"
b10 -
b10 ^
b10 ""
b1 N
b1 #"
b1 4"
b10 !"
b111 .
b111 _
b111 {
b10 O
b10 |
b10 /"
b11 k
b11 z
b11 }
b1010 /
b1010 `
b1010 v
b1 P
b1 w
b1 *"
b100 l
b100 u
b100 x
b0 m
b0 p
b0 s
b1 ;
b1 E
b1 ~
b10 :
b10 D
b10 y
b1 9
b1 C
b1 t
b1110 4
b1110 A
b1110 L"
b1011 3
b1011 @
b1011 8"
b1000 2
b1000 ?
b1000 $"
b0 1
b0 >
b0 n
15
#110
05
#115
b0 P
b0 w
b0 *"
b0 l
b0 u
b0 x
b0 O
b0 |
b0 /"
b100 k
b100 z
b100 }
b0 N
b0 #"
b0 4"
b11 !"
b0 j
b0 &"
b0 )"
b11010 +
b11010 \
b11010 ,"
b1 L
b1 -"
b1 >"
b1000 i
b1000 +"
b1000 ."
b10011 *
b10011 [
b10011 1"
b10 K
b10 2"
b10 C"
b111 h
b111 0"
b111 3"
b110 )
b110 Z
b110 6"
b1 J
b1 7"
b1 H"
b110 5"
b0 I
b0 <"
b0 M"
b1100 g
b1100 :"
b1100 ="
b0 H
b0 A"
b0 R"
b1011 f
b1011 ?"
b1011 B"
b0 G
b0 F"
b0 W"
b1010 e
b1010 D"
b1010 G"
b1001 I"
b101001 $
b101001 U
b101001 O"
b1 P"
b1111 d
b1111 N"
b1111 Q"
b101010 #
b101010 T
b101010 T"
b11 U"
b1110 c
b1110 S"
b1110 V"
b1101 "
b1101 S
b1101 Y"
b1 Z"
b1101 b
b1101 X"
b1101 ["
b0 ;
b0 E
b0 ~
b0 :
b0 D
b0 y
b0 9
b0 C
b0 t
b1111 4
b1111 A
b1111 L"
b1100 3
b1100 @
b1100 8"
b0 2
b0 ?
b0 $"
15
#120
05
#125
b1101 ]"
b0 Z"
b1110 b
b1110 X"
b1110 ["
b0 U"
b1111 c
b1111 S"
b1111 V"
b0 P"
b10000 d
b10000 N"
b10000 Q"
b1010 %
b1010 V
b1010 J"
b1 F
b1 K"
b1 \"
b1010 I"
b11111 &
b11111 W
b11111 E"
b10 G
b10 F"
b10 W"
b1011 e
b1011 D"
b1011 G"
b101010 '
b101010 X
b101010 @"
b1 H
b1 A"
b1 R"
b1100 f
b1100 ?"
b1100 B"
b0 g
b0 :"
b0 ="
b0 J
b0 7"
b0 H"
b111 5"
b0 K
b0 2"
b0 C"
b1000 h
b1000 0"
b1000 3"
b0 L
b0 -"
b0 >"
b0 i
b0 +"
b0 ."
b1110 -
b1110 ^
b1110 ""
b11 N
b11 #"
b11 4"
b100 !"
b0 k
b0 z
b0 }
b11 ;
b11 E
b11 ~
b10000 4
b10000 A
b10000 L"
b0 3
b0 @
b0 8"
15
#130
05
#135
b0 N
b0 #"
b0 4"
b0 !"
b0 h
b0 0"
b0 3"
b11110 )
b11110 Z
b11110 6"
b11 J
b11 7"
b11 H"
b1000 5"
b0 H
b0 A"
b0 R"
b0 f
b0 ?"
b0 B"
b0 G
b0 F"
b0 W"
b1100 e
b1100 D"
b1100 G"
b0 F
b0 K"
b0 \"
b1011 I"
b0 d
b0 N"
b0 Q"
b111010 #
b111010 T
b111010 T"
b1 U"
b10000 c
b10000 S"
b10000 V"
b101011 "
b101011 S
b101011 Y"
b10 Z"
b1111 b
b1111 X"
b1111 ["
b1110 !
b1110 R
b1110 ^"
b1 _"
b1110 ]"
b0 ;
b0 E
b0 ~
b0 4
b0 A
b0 L"
15
#140
05
#145
b0 _"
b1111 ]"
b0 Z"
b10000 b
b10000 X"
b10000 ["
b0 U"
b0 c
b0 S"
b0 V"
b101110 %
b101110 V
b101110 J"
b11 F
b11 K"
b11 \"
b1100 I"
b0 e
b0 D"
b0 G"
b0 J
b0 7"
b0 H"
b0 5"
15
#150
05
#155
b0 F
b0 K"
b0 \"
b0 I"
b0 b
b0 X"
b0 ["
b111110 !
b111110 R
b111110 ^"
b11 _"
b10000 ]"
15
#160
05
#165
b0 _"
b0 ]"
15
#170
05
#175
15
#180
05
#185
b0 <
b100 =
15
