rtl/pe.v
module pe (
    input  wire        clk, rst_n,
    input  wire        en,
    input  wire [7:0]  a_in,      // from left
    input  wire [7:0]  w_in,      // weight from top
    output reg  [7:0]  a_out,     // pass right
    output reg  [7:0]  w_out,     // pass down
    output reg  [31:0] acc        // accumulated sum
);
    always @(posedge clk or negedge rst_n) begin
        if (!rst_n) begin
            a_out <= 0;
            w_out <= 0;
            acc   <= 0;
        end else if (en) begin
            a_out <= a_in;           // pass activation right
            w_out <= w_in;           // pass weight down
            acc   <= acc + (a_in * w_in);  // MAC
        end
    end
endmodule

rtl/systolic_4x4.v
module systolic_4x4 (
    input  wire        clk, rst_n, en,
    // Row inputs (activations) - one per row
    input  wire [7:0]  a_row0, a_row1, a_row2, a_row3,
    // Col inputs (weights) - one per col
    input  wire [7:0]  w_col0, w_col1, w_col2, w_col3,
    // Output accumulators - all 16 results
    output wire [31:0] out_00, out_01, out_02, out_03,
    output wire [31:0] out_10, out_11, out_12, out_13,
    output wire [31:0] out_20, out_21, out_22, out_23,
    output wire [31:0] out_30, out_31, out_32, out_33
);
    // Horizontal wires (activations flowing right)
    wire [7:0] a_00_01, a_01_02, a_02_03;
    wire [7:0] a_10_11, a_11_12, a_12_13;
    wire [7:0] a_20_21, a_21_22, a_22_23;
    wire [7:0] a_30_31, a_31_32, a_32_33;

    // Vertical wires (weights flowing down)
    wire [7:0] w_00_10, w_10_20, w_20_30;
    wire [7:0] w_01_11, w_11_21, w_21_31;
    wire [7:0] w_02_12, w_12_22, w_22_32;
    wire [7:0] w_03_13, w_13_23, w_23_33;

    // Row 0
    pe pe_00(.clk(clk),.rst_n(rst_n),.en(en),.a_in(a_row0),.w_in(w_col0),.a_out(a_00_01),.w_out(w_00_10),.acc(out_00));
    pe pe_01(.clk(clk),.rst_n(rst_n),.en(en),.a_in(a_00_01),.w_in(w_col1),.a_out(a_01_02),.w_out(w_01_11),.acc(out_01));
    pe pe_02(.clk(clk),.rst_n(rst_n),.en(en),.a_in(a_01_02),.w_in(w_col2),.a_out(a_02_03),.w_out(w_02_12),.acc(out_02));
    pe pe_03(.clk(clk),.rst_n(rst_n),.en(en),.a_in(a_02_03),.w_in(w_col3),.a_out(),.w_out(w_03_13),.acc(out_03));

    // Row 1
    pe pe_10(.clk(clk),.rst_n(rst_n),.en(en),.a_in(a_row1),.w_in(w_00_10),.a_out(a_10_11),.w_out(w_10_20),.acc(out_10));
    pe pe_11(.clk(clk),.rst_n(rst_n),.en(en),.a_in(a_10_11),.w_in(w_01_11),.a_out(a_11_12),.w_out(w_11_21),.acc(out_11));
    pe pe_12(.clk(clk),.rst_n(rst_n),.en(en),.a_in(a_11_12),.w_in(w_02_12),.a_out(a_12_13),.w_out(w_12_22),.acc(out_12));
    pe pe_13(.clk(clk),.rst_n(rst_n),.en(en),.a_in(a_12_13),.w_in(w_03_13),.a_out(),.w_out(w_13_23),.acc(out_13));

    // Row 2
    pe pe_20(.clk(clk),.rst_n(rst_n),.en(en),.a_in(a_row2),.w_in(w_10_20),.a_out(a_20_21),.w_out(w_20_30),.acc(out_20));
    pe pe_21(.clk(clk),.rst_n(rst_n),.en(en),.a_in(a_20_21),.w_in(w_11_21),.a_out(a_21_22),.w_out(w_21_31),.acc(out_21));
    pe pe_22(.clk(clk),.rst_n(rst_n),.en(en),.a_in(a_21_22),.w_in(w_12_22),.a_out(a_22_23),.w_out(w_22_32),.acc(out_22));
    pe pe_23(.clk(clk),.rst_n(rst_n),.en(en),.a_in(a_22_23),.w_in(w_13_23),.a_out(),.w_out(w_23_33),.acc(out_23));

    // Row 3
    pe pe_30(.clk(clk),.rst_n(rst_n),.en(en),.a_in(a_row3),.w_in(w_20_30),.a_out(a_30_31),.w_out(),.acc(out_30));
    pe pe_31(.clk(clk),.rst_n(rst_n),.en(en),.a_in(a_30_31),.w_in(w_21_31),.a_out(a_31_32),.w_out(),.acc(out_31));
    pe pe_32(.clk(clk),.rst_n(rst_n),.en(en),.a_in(a_31_32),.w_in(w_22_32),.a_out(a_32_33),.w_out(),.acc(out_32));
    pe pe_33(.clk(clk),.rst_n(rst_n),.en(en),.a_in(a_32_33),.w_in(w_23_33),.a_out(),.w_out(),.acc(out_33));

endmodule

tb/tb_systolic.v
`timescale 1ns/1ns
module tb_systolic;

    reg clk, rst_n, en;

    // Activation inputs (rows of A, fed skewed)
    reg [7:0] a_row0, a_row1, a_row2, a_row3;
    // Weight inputs (cols of B, fed skewed)
    reg [7:0] w_col0, w_col1, w_col2, w_col3;

    // Outputs
    wire [31:0] out_00, out_01, out_02, out_03;
    wire [31:0] out_10, out_11, out_12, out_13;
    wire [31:0] out_20, out_21, out_22, out_23;
    wire [31:0] out_30, out_31, out_32, out_33;

    // DUT
    systolic_4x4 dut (
        .clk(clk), .rst_n(rst_n), .en(en),
        .a_row0(a_row0), .a_row1(a_row1),
        .a_row2(a_row2), .a_row3(a_row3),
        .w_col0(w_col0), .w_col1(w_col1),
        .w_col2(w_col2), .w_col3(w_col3),
        .out_00(out_00), .out_01(out_01),
        .out_02(out_02), .out_03(out_03),
        .out_10(out_10), .out_11(out_11),
        .out_12(out_12), .out_13(out_13),
        .out_20(out_20), .out_21(out_21),
        .out_22(out_22), .out_23(out_23),
        .out_30(out_30), .out_31(out_31),
        .out_32(out_32), .out_33(out_33)
    );

    always #5 clk = ~clk;

    // A matrix rows
    reg [7:0] A [0:3][0:3];
    // B matrix cols
    reg [7:0] B [0:3][0:3];
    // Expected C
    integer C [0:3][0:3];

    integer i, j, k, pass, fail;

    initial begin
        $dumpfile("sim/systolic.vcd");
        $dumpvars(0, tb_systolic);

        clk=0; rst_n=0; en=0;
        a_row0=0; a_row1=0; a_row2=0; a_row3=0;
        w_col0=0; w_col1=0; w_col2=0; w_col3=0;

        // Matrix A
        A[0][0]=1;  A[0][1]=2;  A[0][2]=3;  A[0][3]=4;
        A[1][0]=5;  A[1][1]=6;  A[1][2]=7;  A[1][3]=8;
        A[2][0]=9;  A[2][1]=10; A[2][2]=11; A[2][3]=12;
        A[3][0]=13; A[3][1]=14; A[3][2]=15; A[3][3]=16;

        // Matrix B = Identity
        for (i=0;i<4;i=i+1)
            for (j=0;j<4;j=j+1)
                B[i][j] = (i==j) ? 1 : 0;

        // Compute expected C = A x B
        for (i=0;i<4;i=i+1)
            for (j=0;j<4;j=j+1) begin
                C[i][j] = 0;
                for (k=0;k<4;k=k+1)
                    C[i][j] = C[i][j] + A[i][k]*B[k][j];
            end

        repeat(4) @(posedge clk);
        rst_n = 1;
        en    = 1;
        repeat(2) @(posedge clk);

        // Feed data skewed (systolic diagonal feeding)
        // Cycle 1
        @(posedge clk);
        a_row0=A[0][0]; a_row1=0;        a_row2=0;        a_row3=0;
        w_col0=B[0][0]; w_col1=0;        w_col2=0;        w_col3=0;

        // Cycle 2
        @(posedge clk);
        a_row0=A[0][1]; a_row1=A[1][0];  a_row2=0;        a_row3=0;
        w_col0=B[1][0]; w_col1=B[0][1];  w_col2=0;        w_col3=0;

        // Cycle 3
        @(posedge clk);
        a_row0=A[0][2]; a_row1=A[1][1];  a_row2=A[2][0];  a_row3=0;
        w_col0=B[2][0]; w_col1=B[1][1];  w_col2=B[0][2];  w_col3=0;

        // Cycle 4
        @(posedge clk);
        a_row0=A[0][3]; a_row1=A[1][2];  a_row2=A[2][1];  a_row3=A[3][0];
        w_col0=B[3][0]; w_col1=B[2][1];  w_col2=B[1][2];  w_col3=B[0][3];

        // Cycle 5
        @(posedge clk);
        a_row0=0;       a_row1=A[1][3];  a_row2=A[2][2];  a_row3=A[3][1];
        w_col0=0;       w_col1=B[3][1];  w_col2=B[2][2];  w_col3=B[1][3];

        // Cycle 6
        @(posedge clk);
        a_row0=0;       a_row1=0;        a_row2=A[2][3];  a_row3=A[3][2];
        w_col0=0;       w_col1=0;        w_col2=B[3][2];  w_col3=B[2][3];

        // Cycle 7
        @(posedge clk);
        a_row0=0;       a_row1=0;        a_row2=0;        a_row3=A[3][3];
        w_col0=0;       w_col1=0;        w_col2=0;        w_col3=B[3][3];

        // Drain pipeline
        @(posedge clk); a_row0=0; a_row1=0; a_row2=0; a_row3=0;
                        w_col0=0; w_col1=0; w_col2=0; w_col3=0;
        repeat(5) @(posedge clk);

        // Check results
        pass=0; fail=0;
        $display("\n=== Systolic Array 4x4 Results ===");
        $display("RTL Output Matrix C:");

        $display("  [%0d, %0d, %0d, %0d]", out_00, out_01, out_02, out_03);
        $display("  [%0d, %0d, %0d, %0d]", out_10, out_11, out_12, out_13);
        $display("  [%0d, %0d, %0d, %0d]", out_20, out_21, out_22, out_23);
        $display("  [%0d, %0d, %0d, %0d]", out_30, out_31, out_32, out_33);

        $display("\nExpected Matrix C:");
        $display("  [%0d, %0d, %0d, %0d]", C[0][0],C[0][1],C[0][2],C[0][3]);
        $display("  [%0d, %0d, %0d, %0d]", C[1][0],C[1][1],C[1][2],C[1][3]);
        $display("  [%0d, %0d, %0d, %0d]", C[2][0],C[2][1],C[2][2],C[2][3]);
        $display("  [%0d, %0d, %0d, %0d]", C[3][0],C[3][1],C[3][2],C[3][3]);

        // Verify row 0
        if(out_00==C[0][0] && out_01==C[0][1] && out_02==C[0][2] && out_03==C[0][3]) begin
            $display("\nRow 0: PASS"); pass=pass+1; end
        else begin $display("\nRow 0: FAIL"); fail=fail+1; end

        // Verify row 1
        if(out_10==C[1][0] && out_11==C[1][1] && out_12==C[1][2] && out_13==C[1][3]) begin
            $display("Row 1: PASS"); pass=pass+1; end
        else begin $display("Row 1: FAIL"); fail=fail+1; end

        // Verify row 2
        if(out_20==C[2][0] && out_21==C[2][1] && out_22==C[2][2] && out_23==C[2][3]) begin
            $display("Row 2: PASS"); pass=pass+1; end
        else begin $display("Row 2: FAIL"); fail=fail+1; end

        // Verify row 3
        if(out_30==C[3][0] && out_31==C[3][1] && out_32==C[3][2] && out_33==C[3][3]) begin
            $display("Row 3: PASS"); pass=pass+1; end
        else begin $display("Row 3: FAIL"); fail=fail+1; end

        $display("\n=== %0d/4 PASS | %0d/4 FAIL ===", pass, fail);
        if (fail==0) $display("*** ALL PASS — Systolic Array Verified! ***");

        $finish;
    end
endmodule

sim/systolic.vcd
$date
	Sun Apr 19 21:20:41 2026
$end
$version
	Icarus Verilog
$end
$timescale
	1ns
$end
$scope module tb_systolic $end
$var wire 32 ! out_33 [31:0] $end
$var wire 32 " out_32 [31:0] $end
$var wire 32 # out_31 [31:0] $end
$var wire 32 $ out_30 [31:0] $end
$var wire 32 % out_23 [31:0] $end
$var wire 32 & out_22 [31:0] $end
$var wire 32 ' out_21 [31:0] $end
$var wire 32 ( out_20 [31:0] $end
$var wire 32 ) out_13 [31:0] $end
$var wire 32 * out_12 [31:0] $end
$var wire 32 + out_11 [31:0] $end
$var wire 32 , out_10 [31:0] $end
$var wire 32 - out_03 [31:0] $end
$var wire 32 . out_02 [31:0] $end
$var wire 32 / out_01 [31:0] $end
$var wire 32 0 out_00 [31:0] $end
$var reg 8 1 a_row0 [7:0] $end
$var reg 8 2 a_row1 [7:0] $end
$var reg 8 3 a_row2 [7:0] $end
$var reg 8 4 a_row3 [7:0] $end
$var reg 1 5 clk $end
$var reg 1 6 en $end
$var reg 1 7 rst_n $end
$var reg 8 8 w_col0 [7:0] $end
$var reg 8 9 w_col1 [7:0] $end
$var reg 8 : w_col2 [7:0] $end
$var reg 8 ; w_col3 [7:0] $end
$var integer 32 < fail [31:0] $end
$var integer 32 = i [31:0] $end
$var integer 32 > j [31:0] $end
$var integer 32 ? k [31:0] $end
$var integer 32 @ pass [31:0] $end
$scope module dut $end
$var wire 8 A a_row0 [7:0] $end
$var wire 8 B a_row1 [7:0] $end
$var wire 8 C a_row2 [7:0] $end
$var wire 8 D a_row3 [7:0] $end
$var wire 1 5 clk $end
$var wire 1 6 en $end
$var wire 1 7 rst_n $end
$var wire 8 E w_col0 [7:0] $end
$var wire 8 F w_col1 [7:0] $end
$var wire 8 G w_col2 [7:0] $end
$var wire 8 H w_col3 [7:0] $end
$var wire 8 I w_23_33 [7:0] $end
$var wire 8 J w_22_32 [7:0] $end
$var wire 8 K w_21_31 [7:0] $end
$var wire 8 L w_20_30 [7:0] $end
$var wire 8 M w_13_23 [7:0] $end
$var wire 8 N w_12_22 [7:0] $end
$var wire 8 O w_11_21 [7:0] $end
$var wire 8 P w_10_20 [7:0] $end
$var wire 8 Q w_03_13 [7:0] $end
$var wire 8 R w_02_12 [7:0] $end
$var wire 8 S w_01_11 [7:0] $end
$var wire 8 T w_00_10 [7:0] $end
$var wire 32 U out_33 [31:0] $end
$var wire 32 V out_32 [31:0] $end
$var wire 32 W out_31 [31:0] $end
$var wire 32 X out_30 [31:0] $end
$var wire 32 Y out_23 [31:0] $end
$var wire 32 Z out_22 [31:0] $end
$var wire 32 [ out_21 [31:0] $end
$var wire 32 \ out_20 [31:0] $end
$var wire 32 ] out_13 [31:0] $end
$var wire 32 ^ out_12 [31:0] $end
$var wire 32 _ out_11 [31:0] $end
$var wire 32 ` out_10 [31:0] $end
$var wire 32 a out_03 [31:0] $end
$var wire 32 b out_02 [31:0] $end
$var wire 32 c out_01 [31:0] $end
$var wire 32 d out_00 [31:0] $end
$var wire 8 e a_32_33 [7:0] $end
$var wire 8 f a_31_32 [7:0] $end
$var wire 8 g a_30_31 [7:0] $end
$var wire 8 h a_22_23 [7:0] $end
$var wire 8 i a_21_22 [7:0] $end
$var wire 8 j a_20_21 [7:0] $end
$var wire 8 k a_12_13 [7:0] $end
$var wire 8 l a_11_12 [7:0] $end
$var wire 8 m a_10_11 [7:0] $end
$var wire 8 n a_02_03 [7:0] $end
$var wire 8 o a_01_02 [7:0] $end
$var wire 8 p a_00_01 [7:0] $end
$scope module pe_00 $end
$var wire 8 q a_in [7:0] $end
$var wire 1 5 clk $end
$var wire 1 6 en $end
$var wire 1 7 rst_n $end
$var wire 8 r w_in [7:0] $end
$var reg 8 s a_out [7:0] $end
$var reg 32 t acc [31:0] $end
$var reg 8 u w_out [7:0] $end
$upscope $end
$scope module pe_01 $end
$var wire 8 v a_in [7:0] $end
$var wire 1 5 clk $end
$var wire 1 6 en $end
$var wire 1 7 rst_n $end
$var wire 8 w w_in [7:0] $end
$var reg 8 x a_out [7:0] $end
$var reg 32 y acc [31:0] $end
$var reg 8 z w_out [7:0] $end
$upscope $end
$scope module pe_02 $end
$var wire 8 { a_in [7:0] $end
$var wire 1 5 clk $end
$var wire 1 6 en $end
$var wire 1 7 rst_n $end
$var wire 8 | w_in [7:0] $end
$var reg 8 } a_out [7:0] $end
$var reg 32 ~ acc [31:0] $end
$var reg 8 !" w_out [7:0] $end
$upscope $end
$scope module pe_03 $end
$var wire 8 "" a_in [7:0] $end
$var wire 1 5 clk $end
$var wire 1 6 en $end
$var wire 1 7 rst_n $end
$var wire 8 #" w_in [7:0] $end
$var reg 8 $" a_out [7:0] $end
$var reg 32 %" acc [31:0] $end
$var reg 8 &" w_out [7:0] $end
$upscope $end
$scope module pe_10 $end
$var wire 8 '" a_in [7:0] $end
$var wire 1 5 clk $end
$var wire 1 6 en $end
$var wire 1 7 rst_n $end
$var wire 8 (" w_in [7:0] $end
$var reg 8 )" a_out [7:0] $end
$var reg 32 *" acc [31:0] $end
$var reg 8 +" w_out [7:0] $end
$upscope $end
$scope module pe_11 $end
$var wire 8 ," a_in [7:0] $end
$var wire 1 5 clk $end
$var wire 1 6 en $end
$var wire 1 7 rst_n $end
$var wire 8 -" w_in [7:0] $end
$var reg 8 ." a_out [7:0] $end
$var reg 32 /" acc [31:0] $end
$var reg 8 0" w_out [7:0] $end
$upscope $end
$scope module pe_12 $end
$var wire 8 1" a_in [7:0] $end
$var wire 1 5 clk $end
$var wire 1 6 en $end
$var wire 1 7 rst_n $end
$var wire 8 2" w_in [7:0] $end
$var reg 8 3" a_out [7:0] $end
$var reg 32 4" acc [31:0] $end
$var reg 8 5" w_out [7:0] $end
$upscope $end
$scope module pe_13 $end
$var wire 8 6" a_in [7:0] $end
$var wire 1 5 clk $end
$var wire 1 6 en $end
$var wire 1 7 rst_n $end
$var wire 8 7" w_in [7:0] $end
$var reg 8 8" a_out [7:0] $end
$var reg 32 9" acc [31:0] $end
$var reg 8 :" w_out [7:0] $end
$upscope $end
$scope module pe_20 $end
$var wire 8 ;" a_in [7:0] $end
$var wire 1 5 clk $end
$var wire 1 6 en $end
$var wire 1 7 rst_n $end
$var wire 8 <" w_in [7:0] $end
$var reg 8 =" a_out [7:0] $end
$var reg 32 >" acc [31:0] $end
$var reg 8 ?" w_out [7:0] $end
$upscope $end
$scope module pe_21 $end
$var wire 8 @" a_in [7:0] $end
$var wire 1 5 clk $end
$var wire 1 6 en $end
$var wire 1 7 rst_n $end
$var wire 8 A" w_in [7:0] $end
$var reg 8 B" a_out [7:0] $end
$var reg 32 C" acc [31:0] $end
$var reg 8 D" w_out [7:0] $end
$upscope $end
$scope module pe_22 $end
$var wire 8 E" a_in [7:0] $end
$var wire 1 5 clk $end
$var wire 1 6 en $end
$var wire 1 7 rst_n $end
$var wire 8 F" w_in [7:0] $end
$var reg 8 G" a_out [7:0] $end
$var reg 32 H" acc [31:0] $end
$var reg 8 I" w_out [7:0] $end
$upscope $end
$scope module pe_23 $end
$var wire 8 J" a_in [7:0] $end
$var wire 1 5 clk $end
$var wire 1 6 en $end
$var wire 1 7 rst_n $end
$var wire 8 K" w_in [7:0] $end
$var reg 8 L" a_out [7:0] $end
$var reg 32 M" acc [31:0] $end
$var reg 8 N" w_out [7:0] $end
$upscope $end
$scope module pe_30 $end
$var wire 8 O" a_in [7:0] $end
$var wire 1 5 clk $end
$var wire 1 6 en $end
$var wire 1 7 rst_n $end
$var wire 8 P" w_in [7:0] $end
$var reg 8 Q" a_out [7:0] $end
$var reg 32 R" acc [31:0] $end
$var reg 8 S" w_out [7:0] $end
$upscope $end
$scope module pe_31 $end
$var wire 8 T" a_in [7:0] $end
$var wire 1 5 clk $end
$var wire 1 6 en $end
$var wire 1 7 rst_n $end
$var wire 8 U" w_in [7:0] $end
$var reg 8 V" a_out [7:0] $end
$var reg 32 W" acc [31:0] $end
$var reg 8 X" w_out [7:0] $end
$upscope $end
$scope module pe_32 $end
$var wire 8 Y" a_in [7:0] $end
$var wire 1 5 clk $end
$var wire 1 6 en $end
$var wire 1 7 rst_n $end
$var wire 8 Z" w_in [7:0] $end
$var reg 8 [" a_out [7:0] $end
$var reg 32 \" acc [31:0] $end
$var reg 8 ]" w_out [7:0] $end
$upscope $end
$scope module pe_33 $end
$var wire 8 ^" a_in [7:0] $end
$var wire 1 5 clk $end
$var wire 1 6 en $end
$var wire 1 7 rst_n $end
$var wire 8 _" w_in [7:0] $end
$var reg 8 `" a_out [7:0] $end
$var reg 32 a" acc [31:0] $end
$var reg 8 b" w_out [7:0] $end
$upscope $end
$upscope $end
$upscope $end
$enddefinitions $end
#0
$dumpvars
b0 b"
b0 a"
b0 `"
b0 _"
b0 ^"
b0 ]"
b0 \"
b0 ["
b0 Z"
b0 Y"
b0 X"
b0 W"
b0 V"
b0 U"
b0 T"
b0 S"
b0 R"
b0 Q"
b0 P"
b0 O"
b0 N"
b0 M"
b0 L"
b0 K"
b0 J"
b0 I"
b0 H"
b0 G"
b0 F"
b0 E"
b0 D"
b0 C"
b0 B"
b0 A"
b0 @"
b0 ?"
b0 >"
b0 ="
b0 <"
b0 ;"
b0 :"
b0 9"
b0 8"
b0 7"
b0 6"
b0 5"
b0 4"
b0 3"
b0 2"
b0 1"
b0 0"
b0 /"
b0 ."
b0 -"
b0 ,"
b0 +"
b0 *"
b0 )"
b0 ("
b0 '"
b0 &"
b0 %"
b0 $"
b0 #"
b0 ""
b0 !"
b0 ~
b0 }
b0 |
b0 {
b0 z
b0 y
b0 x
b0 w
b0 v
b0 u
b0 t
b0 s
b0 r
b0 q
b0 p
b0 o
b0 n
b0 m
b0 l
b0 k
b0 j
b0 i
b0 h
b0 g
b0 f
b0 e
b0 d
b0 c
b0 b
b0 a
b0 `
b0 _
b0 ^
b0 ]
b0 \
b0 [
b0 Z
b0 Y
b0 X
b0 W
b0 V
b0 U
b0 T
b0 S
b0 R
b0 Q
b0 P
b0 O
b0 N
b0 M
b0 L
b0 K
b0 J
b0 I
b0 H
b0 G
b0 F
b0 E
b0 D
b0 C
b0 B
b0 A
bx @
b100 ?
b100 >
b100 =
bx <
b0 ;
b0 :
b0 9
b0 8
07
06
05
b0 4
b0 3
b0 2
b0 1
b0 0
b0 /
b0 .
b0 -
b0 ,
b0 +
b0 *
b0 )
b0 (
b0 '
b0 &
b0 %
b0 $
b0 #
b0 "
b0 !
$end
#5
15
#10
05
#15
15
#20
05
#25
15
#30
05
#35
16
17
15
#40
05
#45
15
#50
05
#55
15
#60
05
#65
b1 0
b1 d
b1 t
b1 T
b1 u
b1 ("
b1 p
b1 s
b1 v
b1 8
b1 E
b1 r
b1 1
b1 A
b1 q
15
#70
05
#75
b0 T
b0 u
b0 ("
b10 p
b10 s
b10 v
b1 o
b1 x
b1 {
b101 ,
b101 `
b101 *"
b1 P
b1 +"
b1 <"
b101 m
b101 )"
b101 ,"
b0 8
b0 E
b0 r
b101 2
b101 B
b101 '"
b10 1
b10 A
b10 q
15
#80
05
#85
b1001 (
b1001 \
b1001 >"
b1 L
b1 ?"
b1 P"
b1001 j
b1001 ="
b1001 @"
b101 l
b101 ."
b101 1"
b0 P
b0 +"
b0 <"
b110 m
b110 )"
b110 ,"
b1 n
b1 }
b1 ""
b10 /
b10 c
b10 y
b1 S
b1 z
b1 -"
b10 o
b10 x
b10 {
b11 p
b11 s
b11 v
b1 9
b1 F
b1 w
b1001 3
b1001 C
b1001 ;"
b110 2
b110 B
b110 '"
b11 1
b11 A
b11 q
15
#90
05
#95
b100 p
b100 s
b100 v
b0 S
b0 z
b0 -"
b11 o
b11 x
b11 {
b10 n
b10 }
b10 ""
b1 $"
b111 m
b111 )"
b111 ,"
b110 +
b110 _
b110 /"
b1 O
b1 0"
b1 A"
b110 l
b110 ."
b110 1"
b101 k
b101 3"
b101 6"
b0 L
b0 ?"
b0 P"
b1010 j
b1010 ="
b1010 @"
b1001 i
b1001 B"
b1001 E"
b1101 $
b1101 X
b1101 R"
b1 S"
b1101 g
b1101 Q"
b1101 T"
b0 9
b0 F
b0 w
b1101 4
b1101 D
b1101 O"
b1010 3
b1010 C
b1010 ;"
b111 2
b111 B
b111 '"
b100 1
b100 A
b100 q
15
#100
05
#105
b1101 f
b1101 V"
b1101 Y"
b0 S"
b1110 g
b1110 Q"
b1110 T"
b1001 h
b1001 G"
b1001 J"
b1010 '
b1010 [
b1010 C"
b1 K
b1 D"
b1 U"
b1010 i
b1010 B"
b1010 E"
b1011 j
b1011 ="
b1011 @"
b101 8"
b110 k
b110 3"
b110 6"
b0 O
b0 0"
b0 A"
b111 l
b111 ."
b111 1"
b1000 m
b1000 )"
b1000 ,"
b10 $"
b11 .
b11 b
b11 ~
b1 R
b1 !"
b1 2"
b11 n
b11 }
b11 ""
b100 o
b100 x
b100 {
b0 p
b0 s
b0 v
b1 :
b1 G
b1 |
b1110 4
b1110 D
b1110 O"
b1011 3
b1011 C
b1011 ;"
b1000 2
b1000 B
b1000 '"
b0 1
b0 A
b0 q
15
#110
05
#115
b0 o
b0 x
b0 {
b0 R
b0 !"
b0 2"
b100 n
b100 }
b100 ""
b11 $"
b0 m
b0 )"
b0 ,"
b1000 l
b1000 ."
b1000 1"
b111 *
b111 ^
b111 4"
b1 N
b1 5"
b1 F"
b111 k
b111 3"
b111 6"
b110 8"
b1100 j
b1100 ="
b1100 @"
b0 K
b0 D"
b0 U"
b1011 i
b1011 B"
b1011 E"
b1010 h
b1010 G"
b1010 J"
b1001 L"
b1111 g
b1111 Q"
b1111 T"
b1110 #
b1110 W
b1110 W"
b1 X"
b1110 f
b1110 V"
b1110 Y"
b1101 e
b1101 ["
b1101 ^"
b0 :
b0 G
b0 |
b1111 4
b1111 D
b1111 O"
b1100 3
b1100 C
b1100 ;"
b0 2
b0 B
b0 '"
15
#120
05
#125
b1101 `"
b1110 e
b1110 ["
b1110 ^"
b0 X"
b1111 f
b1111 V"
b1111 Y"
b10000 g
b10000 Q"
b10000 T"
b1010 L"
b1011 &
b1011 Z
b1011 H"
b1 J
b1 I"
b1 Z"
b1011 h
b1011 G"
b1011 J"
b1100 i
b1100 B"
b1100 E"
b0 j
b0 ="
b0 @"
b111 8"
b0 N
b0 5"
b0 F"
b1000 k
b1000 3"
b1000 6"
b0 l
b0 ."
b0 1"
b100 -
b100 a
b100 %"
b1 Q
b1 &"
b1 7"
b100 $"
b0 n
b0 }
b0 ""
b1 ;
b1 H
b1 #"
b10000 4
b10000 D
b10000 O"
b0 3
b0 C
b0 ;"
15
#130
05
#135
b0 Q
b0 &"
b0 7"
b0 $"
b0 k
b0 3"
b0 6"
b1000 )
b1000 ]
b1000 9"
b1 M
b1 :"
b1 K"
b1000 8"
b0 i
b0 B"
b0 E"
b0 J
b0 I"
b0 Z"
b1100 h
b1100 G"
b1100 J"
b1011 L"
b0 g
b0 Q"
b0 T"
b10000 f
b10000 V"
b10000 Y"
b1111 "
b1111 V
b1111 \"
b1 ]"
b1111 e
b1111 ["
b1111 ^"
b1110 `"
b0 ;
b0 H
b0 #"
b0 4
b0 D
b0 O"
15
#140
05
#145
b1111 `"
b0 ]"
b10000 e
b10000 ["
b10000 ^"
b0 f
b0 V"
b0 Y"
b1100 %
b1100 Y
b1100 M"
b1 I
b1 N"
b1 _"
b1100 L"
b0 h
b0 G"
b0 J"
b0 M
b0 :"
b0 K"
b0 8"
15
#150
05
#155
b0 I
b0 N"
b0 _"
b0 L"
b0 e
b0 ["
b0 ^"
b10000 !
b10000 U
b10000 a"
b1 b"
b10000 `"
15
#160
05
#165
b0 b"
b0 `"
15
#170
05
#175
15
#180
05
#185
b0 <
b100 @
15
